statuspage.py
statuspage/__init__.py
statuspage/statuspage.py
statuspage/tests.py
statuspage/template/favicon.png
statuspage/template/localizations.js
statuspage/template/logo.png
statuspage/template/statuspage.js
statuspage/template/style.css
statuspage/template/template.html
statuspage/template/translations.ini
statuspage-0.8.1.dist-info/DESCRIPTION.rst
statuspage-0.8.1.dist-info/METADATA
statuspage-0.8.1.dist-info/RECORD
statuspage-0.8.1.dist-info/WHEEL
statuspage-0.8.1.dist-info/entry_points.txt
statuspage-0.8.1.dist-info/metadata.json
statuspage-0.8.1.dist-info/top_level.txt
