Metadata-Version: 2.0
Name: statuspage
Version: 0.8.1
Summary: A statuspage generator that lets you host your statuspage for free on Github.
Home-page: https://github.com/jayfk/statuspage
Author: Jannis Gebauer
Author-email: ja.geb@me.com
License: MIT
Keywords: statuspage
Platform: UNKNOWN
Classifier: Development Status :: 5 - Production/Stable
Classifier: Environment :: Console
Classifier: Intended Audience :: Developers
Classifier: Natural Language :: English
Classifier: License :: OSI Approved :: MIT License
Classifier: Programming Language :: Python
Classifier: Programming Language :: Python :: 2
Classifier: Programming Language :: Python :: 2.7
Classifier: Programming Language :: Python :: 3
Classifier: Programming Language :: Python :: 3.3
Classifier: Programming Language :: Python :: 3.4
Classifier: Programming Language :: Python :: 3.5
Classifier: Programming Language :: Python :: Implementation :: CPython
Classifier: Programming Language :: Python :: Implementation :: PyPy
Classifier: Topic :: Software Development
Requires-Dist: click
Requires-Dist: jinja2
Requires-Dist: markdown2
Requires-Dist: pygithub
Requires-Dist: requests
Requires-Dist: tqdm
